mpyscm.py
mpyscm-0.1.0.dist-info/metadata.json
mpyscm-0.1.0.dist-info/WHEEL
mpyscm-0.1.0.dist-info/METADATA
mpyscm-0.1.0.dist-info/DESCRIPTION.rst
mpyscm-0.1.0.dist-info/entry_points.txt
mpyscm-0.1.0.dist-info/top_level.txt
mpyscm-0.1.0.dist-info/RECORD
