Metadata-Version: 2.0
Name: mpyscm
Version: 0.1.0
Summary: Python SSH config manager
Home-page: https://github.com/moonstruck/mpyscm
Author: Abdullah Al Mamun
Author-email: mamunabms@yahoo.com
License: BSD
Keywords: mpyscm
Platform: UNKNOWN
Classifier: Development Status :: 2 - Pre-Alpha
Classifier: Framework :: Django
Classifier: Intended Audience :: Developers
Classifier: License :: OSI Approved :: BSD License
Classifier: Natural Language :: English
Classifier: Programming Language :: Python :: 2
Classifier: Programming Language :: Python :: 2.7
Classifier: Programming Language :: Python :: 3
Classifier: Programming Language :: Python :: 3.3
Classifier: Programming Language :: Python :: 3.4
Requires-Dist: click (>=3.1)
